Metadata-Version: 1.1
Name: cotimelog
Version: 0.2.0
Summary: mixins for tornado
Home-page: https://github.com/badbye/timelog.git
Author: Yalei Du
Author-email: yaleidu93@gmail.com
License: Apache License, Version 2
Keywords: log,concurrent
Platform: UNKNOWN
Classifier: Development Status :: 3 - Alpha
Classifier: Programming Language :: Python :: 2.6
Classifier: Programming Language :: Python :: 2.7
Classifier: Topic :: Utilities
Classifier: License :: OSI Approved :: Apache Software License
